shengtengconverter/__init__.py
shengtengconverter/onnx2pytorch/__init__.py
shengtengconverter/onnx2pytorch/constants.py
shengtengconverter/onnx2pytorch/helpers.py
shengtengconverter/onnx2pytorch/utils.py
shengtengconverter/onnx2pytorch/convert/__init__.py
shengtengconverter/onnx2pytorch/convert/attribute.py
shengtengconverter/onnx2pytorch/convert/debug.py
shengtengconverter/onnx2pytorch/convert/layer.py
shengtengconverter/onnx2pytorch/convert/model.py
shengtengconverter/onnx2pytorch/convert/operations.py
shengtengconverter/onnx2pytorch/operations/__init__.py
shengtengconverter/onnx2pytorch/operations/add.py
shengtengconverter/onnx2pytorch/operations/base.py
shengtengconverter/onnx2pytorch/operations/batchnorm.py
shengtengconverter/onnx2pytorch/operations/bitshift.py
shengtengconverter/onnx2pytorch/operations/cast.py
shengtengconverter/onnx2pytorch/operations/clip.py
shengtengconverter/onnx2pytorch/operations/constant.py
shengtengconverter/onnx2pytorch/operations/constantofshape.py
shengtengconverter/onnx2pytorch/operations/div.py
shengtengconverter/onnx2pytorch/operations/expand.py
shengtengconverter/onnx2pytorch/operations/flatten.py
shengtengconverter/onnx2pytorch/operations/gather.py
shengtengconverter/onnx2pytorch/operations/gathernd.py
shengtengconverter/onnx2pytorch/operations/globalaveragepool.py
shengtengconverter/onnx2pytorch/operations/instancenorm.py
shengtengconverter/onnx2pytorch/operations/loop.py
shengtengconverter/onnx2pytorch/operations/lstm.py
shengtengconverter/onnx2pytorch/operations/matmul.py
shengtengconverter/onnx2pytorch/operations/nonmaxsuppression.py
shengtengconverter/onnx2pytorch/operations/onehot.py
shengtengconverter/onnx2pytorch/operations/pad.py
shengtengconverter/onnx2pytorch/operations/prelu.py
shengtengconverter/onnx2pytorch/operations/range.py
shengtengconverter/onnx2pytorch/operations/reducesum.py
shengtengconverter/onnx2pytorch/operations/reshape.py
shengtengconverter/onnx2pytorch/operations/resize.py
shengtengconverter-4.0.0.dist-info/METADATA
shengtengconverter-4.0.0.dist-info/WHEEL
shengtengconverter-4.0.0.dist-info/top_level.txt
shengtengconverter-4.0.0.dist-info/RECORD
