Metadata-Version: 2.1
Name: shengtengconverter
Version: 4.0.0
Summary: A simple converter for Shengteng
Home-page: https://github.com/1963306815/shengtengconverter
Author: zhangzhiyang
Author-email: 1963306815@qq.com
License: UNKNOWN
Platform: UNKNOWN
Requires-Python: >=3.6
Requires-Dist: numpy (>=1.24.2)
Requires-Dist: onnx (>=1.13.1)
Requires-Dist: onnx-tf (>=1.10.0)
Requires-Dist: onnxruntime-gpu
Requires-Dist: setuptools (>=56.0.0)
Requires-Dist: tensorflow (>=2.11.0)
Requires-Dist: tf2onnx (>=1.13.0)
Requires-Dist: torch (>=1.11.0)
Requires-Dist: torchvision (>=0.15.2)
Requires-Dist: tensorflow-probability
